LICENSE
MANIFEST.in
README.rst
setup.py
dig/VERSION
dig/__init__.py
dig/cmdline.py
dig/data_io.py
dig/mpg123.exe
dig/record.py
dig/settings.py
dig/share.py
dig/translate.py
dig/translate_api.py
dig.egg-info/PKG-INFO
dig.egg-info/SOURCES.txt
dig.egg-info/dependency_links.txt
dig.egg-info/entry_points.txt
dig.egg-info/requires.txt
dig.egg-info/top_level.txt