Metadata-Version: 1.1
Name: dig
Version: 0.1.10
Summary: Command-line tool of [ google, youdao ] translation service.
Home-page: https://github.com/enjoyhot/dig
Author: Gogary
Author-email: gugugujiawei@gmail.com
License: BSD
Platform: UNKNOWN
Classifier: Development Status :: 3 - Alpha
Classifier: Intended Audience :: End Users/Desktop 
Classifier: Programming Language :: Python
Classifier: Programming Language :: Python :: 2
Classifier: Programming Language :: Python :: 2.7
Classifier: Programming Language :: Python :: 3
Classifier: Operating System :: OS Independent
Classifier: License :: OSI Approved :: BSD License
Classifier: Topic :: Software Development :: Libraries :: Python Modules
